ezweb/__init__.py
ezweb/objects/__init__.py
ezweb/objects/product.py
ezweb/objects/soup.py
ezweb/objects/source.py
ezweb/utils/__init__.py
ezweb/utils/http.py
ezweb/utils/io.py
ezweb/utils/souphelper.py
ezweb/utils/text.py
ezweb-4.4.0.dist-info/LICENSE
ezweb-4.4.0.dist-info/METADATA
ezweb-4.4.0.dist-info/WHEEL
ezweb-4.4.0.dist-info/top_level.txt
ezweb-4.4.0.dist-info/RECORD
