Metadata-Version: 2.1
Name: ezweb
Version: 4.4.0
Summary: An easy to use web page analyzer (scraper or crawler) with many useful features and properties
Home-page: https://github.com/mdmomeni/ezweb
Author: Mohammad Momeni
Author-email: mdmomeny@gmail.com
License: UNKNOWN
Project-URL: Bug Tracker, https://github.com/mdmomeni/ezweb/issues
Platform: UNKNOWN
Classifier: Programming Language :: Python :: 3
Classifier: License :: OSI Approved :: MIT License
Classifier: Operating System :: OS Independent
Requires-Python: >=3.6
License-File: LICENSE
Requires-Dist: requests
Requires-Dist: beautifulsoup4
Requires-Dist: unidecode
Requires-Dist: python-dateutil
Requires-Dist: rapidfuzz
Requires-Dist: readability-lxml
Requires-Dist: trafilatura
Requires-Dist: cached-property
Requires-Dist: feedparser
